nucliadb_dataset/__init__.py
nucliadb_dataset/api.py
nucliadb_dataset/dataset.py
nucliadb_dataset/export.py
nucliadb_dataset/mapping.py
nucliadb_dataset/nuclia.py
nucliadb_dataset/py.typed
nucliadb_dataset/run.py
nucliadb_dataset/settings.py
nucliadb_dataset/streamer.py
nucliadb_dataset/tasks.py
nucliadb_dataset/tests/__init__.py
nucliadb_dataset/tests/fixtures.py
nucliadb_dataset-6.11.1.post5854.dist-info/METADATA
nucliadb_dataset-6.11.1.post5854.dist-info/WHEEL
nucliadb_dataset-6.11.1.post5854.dist-info/entry_points.txt
nucliadb_dataset-6.11.1.post5854.dist-info/top_level.txt
nucliadb_dataset-6.11.1.post5854.dist-info/RECORD
