Metadata-Version: 2.4
Name: nucliadb_dataset
Version: 6.11.1.post5854
Summary: NucliaDB Train Python client
Author-email: Nuclia <nucliadb@nuclia.com>
License-Expression: Apache-2.0
Project-URL: Homepage, https://nuclia.com
Project-URL: Repository, https://github.com/nuclia/nucliadb
Classifier: Development Status :: 3 - Alpha
Classifier: Intended Audience :: Developers
Classifier: Intended Audience :: Information Technology
Classifier: Programming Language :: Python
Classifier: Programming Language :: Python :: 3.10
Classifier: Programming Language :: Python :: 3.11
Classifier: Programming Language :: Python :: 3.12
Classifier: Programming Language :: Python :: 3 :: Only
Requires-Python: <4,>=3.10
Requires-Dist: protobuf
Requires-Dist: types-protobuf
Requires-Dist: grpcio
Requires-Dist: requests
Requires-Dist: aiohttp
Requires-Dist: argdantic
Requires-Dist: pydantic-settings>=2.2
Requires-Dist: pyarrow
Requires-Dist: nucliadb-protos>=6.11.1.post5854
Requires-Dist: nucliadb-sdk>=6.11.1.post5854
Requires-Dist: nucliadb-models>=6.11.1.post5854
